vbcable_output/__init__.py
vbcable_output/vbcable_output.py
vbcable_output-0.1.0.dist-info/LICENSE
vbcable_output-0.1.0.dist-info/METADATA
vbcable_output-0.1.0.dist-info/WHEEL
vbcable_output-0.1.0.dist-info/top_level.txt
vbcable_output-0.1.0.dist-info/RECORD
