Metadata-Version: 2.2
Name: vbcable_output
Version: 0.1.0
Summary: This package outputs audio to the VBCable virtual audio device.
Author-email: nnnnnnn0090 <nnnnnnn0090@gmail.com>
Maintainer-email: nnnnnnn0090 <nnnnnnn0090@gmail.com>
License: MIT
Project-URL: Homepage, https://github.com/nnnnnnn0090/vbcable_output
Project-URL: Issue Tracker, https://github.com/nnnnnnn0090/vbcable_output/issues
Classifier: Programming Language :: Python :: 3
Classifier: License :: OSI Approved :: MIT License
Classifier: Operating System :: OS Independent
Requires-Python: >=3.6
License-File: LICENSE
Requires-Dist: sounddevice
